{"version": 0.6, "generator": "Overpass API 0.7.62.11 87bfad18", "osm3s": {"timestamp_osm_base": "2026-05-13T10:02:21Z", "copyright": "The data included in this document is from www.openstreetmap.org. The data is made available under ODbL."}, "elements": [{"type": "node", "id": 288064990, "lat": 52.2029763, "lon": 0.1208286, "tags": {"bench": "no", "bin": "no", "bus": "yes", "fixme": "Is this in the correct position?", "highway": "bus_stop", "operator": "City Sightseeing", "public_transport": "platform", "ref": "2", "shelter": "yes", "source": "survey"}}, {"type": "node", "id": 290577084, "lat": 52.2025889, "lon": 0.1178278, "tags": {"bus": "yes", "highway": "bus_stop", "note": "CityShuttle stop.  Exact Position is a bit suspect on this.", "public_transport": "platform"}}, {"type": "node", "id": 298290425, "lat": 52.2092559, "lon": 0.127363, "tags": {"bench": "no", "bin": "no", "bus": "yes", "fixme": "Pre-Naptan import; check and verify note=* information.", "highway": "bus_stop", "lit": "no", "name": "Victoria Avenue", "note": "16 and 17 and Citi 7 stop here. No name / ref on overhead sign.", "operator": "Stagecoach", "public_transport": "platform", "shelter": "no", "source": "survey", "tactile_paving": "no"}}, {"type": "node", "id": 298290427, "lat": 52.209245, "lon": 0.1271452, "tags": {"bench": "yes", "bin": "no", "bus": "yes", "check_date:bin": "2023-09-22", "fixme": "Pre-Naptan import; check and verify note=* information.", "highway": "bus_stop", "lit": "no", "name": "Victoria Avenue", "note": "X9, 9, 15, X7, 15A, 16, 17, Citi 7 stop here. No name / ref on overhead sign.", "operator": "Stagecoach", "public_transport": "platform", "shelter": "yes", "source": "survey", "tactile_paving": "no"}}, {"type": "node", "id": 298290451, "lat": 52.2055684, "lon": 0.1187059, "tags": {"bench": "no", "bin": "no", "bus": "yes", "highway": "bus_stop", "lit": "yes", "name": "Market Street", "naptan:AtcoCode": "0500CCITY002", "naptan:Bearing": "S", "naptan:CommonName": "Great St Mary's Church", "naptan:Crossing": "St Mary's Street", "naptan:Indicator": "near", "naptan:Landmark": "Great St Mary's Church", "naptan:NaptanCode": "cmbdadag", "naptan:PlusbusZoneRef": "CAMBDGE", "naptan:ShortCommonName": "Gt St Mary's Church", "naptan:Street": "Trinity Street", "naptan:verified": "yes", "operator": "City Sightseeing", "public_transport": "platform", "shelter": "yes", "source": "naptan_import;survey", "tactile_paving": "no"}}, {"type": "node", "id": 299607148, "lat": 52.2132803, "lon": 0.1211339, "tags": {"alt_name": "Job Centre", "bench": "yes", "bin": "yes", "bus": "yes", "highway": "bus_stop", "lit": "no", "name": "Carlyle Road", "naptan:AltCommonName": "Job Centre", "naptan:AtcoCode": "0500CCITY106", "naptan:Bearing": "SW", "naptan:CommonName": "Carlyle Road", "naptan:Indicator": "opp", "naptan:Landmark": "Carlyle Road", "naptan:NaptanCode": "cmbdajat", "naptan:PlusbusZoneRef": "CAMBDGE", "naptan:ShortCommonName": "Carlyle Road", "naptan:Street": "Chesterton Road", "note": "Chesterton Road stop.;15, 15A, Citi 1 and Citi 2 stop here. Label says \"Cambridge Chesterton Road opp Carlyle Road\" CMBDAJAT", "operator": "City Sightseeing", "public_transport": "platform", "ref": "4", "shelter": "yes", "source": "naptan_import;survey", "tactile_paving": "no", "wheelchair": "yes"}}, {"type": "node", "id": 300452925, "lat": 52.2049781, "lon": 0.1245891, "tags": {"bench": "yes", "bin": "yes", "bus": "yes", "highway": "bus_stop", "lit": "yes", "operator": "City Sightseeing", "public_transport": "platform", "ref": "10", "shelter": "yes", "source": "survey"}}, {"type": "node", "id": 300452937, "lat": 52.2042924, "lon": 0.1227956, "tags": {"bench": "yes", "bin": "yes", "bus": "yes", "check_date:shelter": "2024-03-02", "highway": "bus_stop", "lit": "yes", "name": "S3", "note": "St Andrew's Street stop.  Shares a post / shelter with Stagecoach stop.", "operator": "Citi 8 and Cambridge City Sightseeing (Stagecoach)", "public_transport": "platform", "ref": "3", "shelter": "yes", "source": "survey", "tactile_paving": "no"}}, {"type": "node", "id": 300452938, "lat": 52.204294, "lon": 0.1228052, "tags": {"bench": "yes", "bin": "yes", "bus": "yes", "check_date:shelter": "2024-03-02", "highway": "bus_stop", "lit": "yes", "name": "St. Andrews Street", "note": "14 and Citi 3 stop here.  Shares a post and shelter with City Sightseeing stop.", "operator": "Stagecoach", "public_transport": "platform", "shelter": "yes", "source": "survey", "tactile_paving": "no"}}, {"type": "node", "id": 533790855, "lat": 52.2140007, "lon": 0.1244486, "tags": {"bench": "no", "bin": "yes", "bus": "yes", "highway": "bus_stop", "lit": "yes", "name": "Victoria Road", "naptan:AtcoCode": "0500CCITY019", "naptan:Bearing": "SW", "naptan:CommonName": "Victoria Road", "naptan:Indicator": "opp", "naptan:Landmark": "Victoria Road", "naptan:NaptanCode": "cmbdadjm", "naptan:PlusbusZoneRef": "CAMBDGE", "naptan:ShortCommonName": "Victoria Road", "naptan:Street": "Chesterton Road", "naptan:verified": "no", "public_transport": "platform", "shelter": "no", "source": "naptan_import", "tactile_paving": "no"}}, {"type": "node", "id": 533790856, "lat": 52.2148978, "lon": 0.1279645, "tags": {"bench": "yes", "bin": "yes", "bus": "yes", "highway": "bus_stop", "lit": "yes", "name": "Hamilton Road", "naptan:AtcoCode": "0500CCITY020", "naptan:Bearing": "NE", "naptan:CommonName": "Hamilton Road", "naptan:Indicator": "opp", "naptan:Landmark": "Hamilton Road", "naptan:NaptanCode": "cmbdadjp", "naptan:PlusbusZoneRef": "CAMBDGE", "naptan:ShortCommonName": "Hamilton Road", "naptan:Street": "Chesterton Road", "naptan:verified": "no", "note": "Stop for 16, 17, Citi 2.  Label \"Cambridge  Chesterton Road  opp Hamilton Road\" txt msg ref CMBDADJP.", "public_transport": "platform", "shelter": "yes", "source": "naptan_import", "tactile_paving": "no"}}, {"type": "node", "id": 533790857, "lat": 52.2146902, "lon": 0.1275996, "tags": {"bench": "yes", "bin": "yes", "bus": "yes", "highway": "bus_stop", "lit": "yes", "name": "Hamilton Road", "naptan:AtcoCode": "0500CCITY021", "naptan:Bearing": "SW", "naptan:CommonName": "Hamilton Road", "naptan:Indicator": "near", "naptan:Landmark": "Hamilton Road", "naptan:NaptanCode": "cmbdadjt", "naptan:PlusbusZoneRef": "CAMBDGE", "naptan:ShortCommonName": "Hamilton Road", "naptan:Street": "Chesterton Road", "naptan:verified": "no", "public_transport": "platform", "shelter": "yes", "source": "naptan_import", "tactile_paving": "no"}}, {"type": "node", "id": 533790914, "lat": 52.2062587, "lon": 0.1348954, "tags": {"bench": "yes", "bin": "yes", "bus": "yes", "highway": "bus_stop", "lit": "yes", "local_ref": "A", "name": "Grafton Centre", "naptan:AtcoCode": "0500CCITY069", "naptan:Bearing": "NE", "naptan:CommonName": "Grafton Centre", "naptan:Indicator": "Bay A", "naptan:Landmark": "Grafton Centre", "naptan:NaptanCode": "cmbdagjp", "naptan:PlusbusZoneRef": "CAMBDGE", "naptan:ShortCommonName": "Grafton Bay A", "naptan:Street": "Crispin Place", "naptan:verified": "no", "public_transport": "platform", "shelter": "yes", "source": "naptan_import", "tactile_paving": "no", "wheelchair": "yes"}}, {"type": "node", "id": 533790916, "lat": 52.2026786, "lon": 0.1178074, "tags": {"bus": "yes", "highway": "bus_stop", "name": "Corpus Christi Col", "naptan:AtcoCode": "0500CCITY070", "naptan:Bearing": "S", "naptan:CommonName": "Corpus Christi Col", "naptan:Indicator": "o/s", "naptan:Landmark": "Trumpington Street", "naptan:NaptanCode": "cmbdagjt", "naptan:PlusbusZoneRef": "CAMBDGE", "naptan:ShortCommonName": "Corpus Christi Col", "naptan:Street": "Trumpington Street", "naptan:verified": "no", "note": "*Was* on wrong side of road", "public_transport": "platform", "shelter": "no", "source": "naptan_import"}}, {"type": "node", "id": 533790917, "lat": 52.2075554, "lon": 0.1180198, "tags": {"bench": "no", "bin": "yes", "bus": "yes", "highway": "bus_stop", "lit": "yes", "name": "All Saints Passage", "naptan:AtcoCode": "0500CCITY071", "naptan:Bearing": "S", "naptan:CommonName": "All Saints Passage", "naptan:Indicator": "near", "naptan:Landmark": "All Saints Passage", "naptan:NaptanCode": "cmbdagjw", "naptan:PlusbusZoneRef": "CAMBDGE", "naptan:ShortCommonName": "All Saints Passage", "naptan:Street": "Trinity Street", "naptan:verified": "no", "public_transport": "platform", "shelter": "no", "source": "naptan_import", "tactile_paving": "no"}}, {"type": "node", "id": 533790954, "lat": 52.2147546, "lon": 0.1219486, "tags": {"bench": "no", "bin": "no", "bus": "yes", "highway": "bus_stop", "lit": "yes", "name": "Green's Road", "naptan:AtcoCode": "0500CCITY095", "naptan:Bearing": "E", "naptan:CommonName": "Green's Road", "naptan:Indicator": "near", "naptan:Landmark": "Green's Road", "naptan:NaptanCode": "cmbdagwg", "naptan:PlusbusZoneRef": "CAMBDGE", "naptan:ShortCommonName": "Green's Road", "naptan:Street": "Victoria Road", "public_transport": "platform", "shelter": "no", "source": "naptan_import", "tactile_paving": "no"}}, {"type": "node", "id": 533790956, "lat": 52.2063847, "lon": 0.1348868, "tags": {"bench": "yes", "bin": "yes", "bus": "yes", "highway": "bus_stop", "lit": "yes", "local_ref": "B", "name": "Grafton Centre", "naptan:AtcoCode": "0500CCITY096", "naptan:Bearing": "NE", "naptan:CommonName": "Grafton Centre", "naptan:Indicator": "Bay B", "naptan:Landmark": "Grafton Centre", "naptan:NaptanCode": "cmbdagwj", "naptan:PlusbusZoneRef": "CAMBDGE", "naptan:ShortCommonName": "Grafton Bay B", "naptan:Street": "Crispin Place", "naptan:verified": "no", "public_transport": "platform", "shelter": "yes", "source": "naptan_import", "tactile_paving": "no", "wheelchair": "yes"}}, {"type": "node", "id": 533790960, "lat": 52.2093561, "lon": 0.117201, "tags": {"bench": "yes", "bin": "yes", "bus": "yes", "check_date:shelter": "2025-09-13", "highway": "bus_stop", "lit": "yes", "name": "Bridge Street", "naptan:AtcoCode": "0500CCITY099", "naptan:Bearing": "NW", "naptan:CommonName": "Bridge Street", "naptan:Indicator": "o/s St John's College", "naptan:Landmark": "Bridge Street", "naptan:NaptanCode": "cmbdagwt", "naptan:PlusbusZoneRef": "CAMBDGE", "naptan:ShortCommonName": "Bridge Street", "naptan:Street": "Bridge Street", "naptan:verified": "no", "public_transport": "platform", "shelter": "yes", "source": "naptan_import", "tactile_paving": "no", "wheelchair": "yes"}}, {"type": "node", "id": 533790966, "lat": 52.2083597, "lon": 0.1345717, "tags": {"bench": "yes", "bin": "yes", "bus": "yes", "highway": "bus_stop", "lit": "yes", "name": "Napier Street", "naptan:AtcoCode": "0500CCITY102", "naptan:Bearing": "E", "naptan:CommonName": "Napier Street", "naptan:Indicator": "opp", "naptan:Landmark": "Napier Street", "naptan:NaptanCode": "cmbdajaj", "naptan:PlusbusZoneRef": "CAMBDGE", "naptan:ShortCommonName": "Napier Street", "naptan:Street": "Newmarket Road", "naptan:verified": "no", "public_transport": "platform", "shelter": "no", "source": "naptan_import", "tactile_paving": "no"}}, {"type": "node", "id": 533790968, "lat": 52.2082122, "lon": 0.1342719, "tags": {"bench": "no", "bin": "no", "bus": "yes", "highway": "bus_stop", "lit": "yes", "name": "Napier Street", "naptan:AtcoCode": "0500CCITY103", "naptan:Bearing": "W", "naptan:CommonName": "Napier Street", "naptan:Indicator": "near", "naptan:Landmark": "Napier Street", "naptan:NaptanCode": "cmbdajam", "naptan:PlusbusZoneRef": "CAMBDGE", "naptan:ShortCommonName": "Napier Street", "naptan:Street": "Newmarket Road", "naptan:verified": "no", "public_transport": "platform", "shelter": "yes", "source": "naptan_import", "tactile_paving": "no"}}, {"type": "node", "id": 533790971, "lat": 52.2079184, "lon": 0.1281396, "tags": {"bench": "yes", "bin": "no", "bus": "yes", "highway": "bus_stop", "lit": "yes", "name": "Fair Street", "naptan:AtcoCode": "0500CCITY104", "naptan:Bearing": "E", "naptan:CommonName": "Fair Street", "naptan:Indicator": "opp", "naptan:Landmark": "Victoria Avenue", "naptan:NaptanCode": "cmbdajap", "naptan:PlusbusZoneRef": "CAMBDGE", "naptan:ShortCommonName": "Fair Street", "naptan:Street": "Maids Causeway", "naptan:verified": "no", "public_transport": "platform", "shelter": "yes", "source": "naptan_import", "tactile_paving": "no"}}, {"type": "node", "id": 533790973, "lat": 52.21338, "lon": 0.1210229, "tags": {"alt_name": "Job Centre", "bench": "no", "bin": "no", "bus": "yes", "highway": "bus_stop", "lit": "yes", "name": "Carlyle Road", "naptan:AltCommonName": "Job Centre", "naptan:AtcoCode": "0500CCITY107", "naptan:Bearing": "NE", "naptan:CommonName": "Carlyle Road", "naptan:Indicator": "near", "naptan:Landmark": "Carlyle Road", "naptan:NaptanCode": "cmbdajaw", "naptan:PlusbusZoneRef": "CAMBDGE", "naptan:ShortCommonName": "Carlyle Road", "naptan:Street": "Chesterton Road", "note": "Stop for Citi 1, Citi 2, 15, 15A. Label \"Cambridge Chesterton Road Carlyle Road\", txt msg ref CMBDAJAW", "operator": "Stagecoach", "public_transport": "platform", "shelter": "no", "source": "naptan_import;survey", "tactile_paving": "no", "wheelchair": "yes"}}, {"type": "node", "id": 533790975, "lat": 52.2121399, "lon": 0.1180392, "tags": {"bench": "no", "bin": "no", "bus": "yes", "highway": "bus_stop", "lit": "yes", "name": "Hertford Street", "naptan:AtcoCode": "0500CCITY108", "naptan:Bearing": "SW", "naptan:CommonName": "Hertford Street", "naptan:Indicator": "opp", "naptan:Landmark": "Hertford Street", "naptan:NaptanCode": "cmbdajda", "naptan:PlusbusZoneRef": "CAMBDGE", "naptan:ShortCommonName": "Hertford Street", "naptan:Street": "Chesterton Road", "naptan:verified": "no", "public_transport": "platform", "shelter": "no", "source": "naptan_import", "tactile_paving": "no"}}, {"type": "node", "id": 533790978, "lat": 52.208501, "lon": 0.1272724, "tags": {"bench": "no", "bin": "no", "bus": "yes", "highway": "bus_stop", "lit": "yes", "name": "Jesus College", "naptan:AtcoCode": "0500CCITY109", "naptan:Bearing": "S", "naptan:CommonName": "Jesus College", "naptan:Indicator": "opp", "naptan:Landmark": "Jesus College", "naptan:NaptanCode": "cmbdajdg", "naptan:PlusbusZoneRef": "CAMBDGE", "naptan:ShortCommonName": "Victoria Avenue", "naptan:Street": "Victoria Avenue", "naptan:verified": "no", "public_transport": "platform", "shelter": "no", "source": "naptan_import", "tactile_paving": "no"}}, {"type": "node", "id": 533790979, "lat": 52.2085634, "lon": 0.1270643, "tags": {"bench": "yes", "bin": "yes", "bus": "yes", "highway": "bus_stop", "lit": "yes", "name": "Jesus College", "naptan:AtcoCode": "0500CCITY110", "naptan:Bearing": "N", "naptan:CommonName": "Jesus College", "naptan:Indicator": "o/s", "naptan:Landmark": "Jesus College", "naptan:NaptanCode": "cmbdajdj", "naptan:PlusbusZoneRef": "CAMBDGE", "naptan:ShortCommonName": "Victoria Avenue", "naptan:Street": "Victoria Avenue", "naptan:verified": "no", "public_transport": "platform", "shelter": "yes", "source": "naptan_import", "tactile_paving": "no"}}, {"type": "node", "id": 533790980, "lat": 52.2063648, "lon": 0.1215306, "tags": {"bench": "no", "bin": "no", "bus": "yes", "highway": "bus_stop", "lit": "no", "maintainer": "Stagecoach", "name": "Christ's College", "naptan:AtcoCode": "0500CCITY111", "naptan:Bearing": "N", "naptan:CommonName": "Christ's College", "naptan:Indicator": "opp", "naptan:Landmark": "Christ's College", "naptan:NaptanCode": "cmbdajdm", "naptan:PlusbusZoneRef": "CAMBDGE", "naptan:ShortCommonName": "Christ's College", "naptan:Street": "Hobson Street", "naptan:verified": "yes", "operator": "Stagecoach", "public_transport": "platform", "shelter": "no", "source": "naptan_import", "tactile_paving": "no"}}, {"type": "node", "id": 533790983, "lat": 52.2053933, "lon": 0.1239259, "tags": {"bench": "yes", "bin": "yes", "bus": "yes", "highway": "bus_stop", "lit": "yes", "local_ref": "6", "name": "Drummer St Bus Station", "naptan:AtcoCode": "0500CCITY114", "naptan:CommonName": "Drummer St Bus Station", "naptan:Indicator": "Bay 6", "naptan:Landmark": "Bus Station", "naptan:NaptanCode": "cmbdajdw", "naptan:PlusbusZoneRef": "CAMBDGE", "naptan:ShortCommonName": "Bus Station Bay 6", "naptan:Street": "Drummer Street", "naptan:verified": "no", "public_transport": "platform", "shelter": "yes", "source": "naptan_import", "tactile_paving": "no"}}, {"type": "node", "id": 533790987, "lat": 52.2052456, "lon": 0.1243013, "tags": {"bench": "yes", "bin": "yes", "bus": "yes", "highway": "bus_stop", "lit": "yes", "local_ref": "12", "name": "Drummer St Bus Station", "naptan:AtcoCode": "0500CCITY116", "naptan:CommonName": "Drummer St Bus Station", "naptan:Indicator": "Bay 12", "naptan:Landmark": "Bus Station", "naptan:NaptanCode": "cmbdajgd", "naptan:PlusbusZoneRef": "CAMBDGE", "naptan:ShortCommonName": "Drummer St Bay 12", "naptan:Street": "Drummer Street", "naptan:verified": "no", "public_transport": "platform", "shelter": "yes", "source": "naptan_import", "tactile_paving": "no"}}, {"type": "node", "id": 533790989, "lat": 52.2028531, "lon": 0.130283, "tags": {"bench": "yes", "bin": "yes", "bus": "yes", "highway": "bus_stop", "lit": "yes", "name": "The Busway Parkside", "naptan:AtcoCode": "0500CCITY117", "naptan:Bearing": "NW", "naptan:CommonName": "The Busway Parkside", "naptan:Indicator": "NW-bound", "naptan:Landmark": "Fire Station", "naptan:NaptanCode": "cmbdajgj", "naptan:PlusbusZoneRef": "CAMBDGE", "naptan:ShortCommonName": "Busway Parkside", "naptan:Street": "Parkside", "naptan:verified": "no", "public_transport": "platform", "shelter": "yes", "source": "naptan_import", "tactile_paving": "yes"}}, {"type": "node", "id": 533790991, "lat": 52.2054897, "lon": 0.1236912, "tags": {"bench": "yes", "bin": "yes", "bus": "yes", "highway": "bus_stop", "lit": "yes", "local_ref": "2", "name": "Drummer St Bus Station", "naptan:AtcoCode": "0500CCITY118", "naptan:CommonName": "Drummer St Bus Station", "naptan:Indicator": "Bay 2", "naptan:Landmark": "Bus Station", "naptan:NaptanCode": "cmbdajgm", "naptan:PlusbusZoneRef": "CAMBDGE", "naptan:ShortCommonName": "Drummer St Bay 2", "naptan:Street": "Drummer Street", "naptan:verified": "no", "public_transport": "platform", "shelter": "yes", "source": "naptan_import", "tactile_paving": "no"}}, {"type": "node", "id": 533790994, "lat": 52.2054707, "lon": 0.1237488, "tags": {"bench": "yes", "bin": "yes", "bus": "yes", "highway": "bus_stop", "lit": "yes", "local_ref": "3", "name": "Drummer St Bus Station", "naptan:AtcoCode": "0500CCITY119", "naptan:CommonName": "Drummer St Bus Station", "naptan:Indicator": "Bay 3", "naptan:Landmark": "Bus Station", "naptan:NaptanCode": "cmbdajgp", "naptan:PlusbusZoneRef": "CAMBDGE", "naptan:ShortCommonName": "Drummer St Bay 3", "naptan:Street": "Drummer Street", "naptan:verified": "no", "public_transport": "platform", "shelter": "yes", "source": "naptan_import", "tactile_paving": "no"}}, {"type": "node", "id": 533790997, "lat": 52.2054144, "lon": 0.1238779, "tags": {"bench": "yes", "bin": "yes", "bus": "yes", "highway": "bus_stop", "lit": "yes", "local_ref": "5", "name": "Drummer St Bus Station", "naptan:AtcoCode": "0500CCITY121", "naptan:CommonName": "Drummer St Bus Station", "naptan:Indicator": "Bay 5", "naptan:Landmark": "Bus Station", "naptan:NaptanCode": "cmbdajgw", "naptan:PlusbusZoneRef": "CAMBDGE", "naptan:ShortCommonName": "Drummer St Bay 5", "naptan:Street": "Drummer Street", "naptan:verified": "no", "public_transport": "platform", "shelter": "yes", "source": "naptan_import", "tactile_paving": "no"}}, {"type": "node", "id": 533790999, "lat": 52.2087081, "lon": 0.1180905, "tags": {"bench": "yes", "bin": "yes", "bus": "yes", "check_date:shelter": "2025-09-18", "highway": "bus_stop", "lit": "yes", "name": "Bridge Street", "naptan:AtcoCode": "0500CCITY122", "naptan:Bearing": "NW", "naptan:CommonName": "Bridge Street", "naptan:Indicator": "opp Round Church", "naptan:Landmark": "Round Church Street", "naptan:NaptanCode": "cmbdajma", "naptan:PlusbusZoneRef": "CAMBDGE", "naptan:ShortCommonName": "Bridge Street", "naptan:Street": "Bridge Street", "naptan:verified": "no", "public_transport": "platform", "shelter": "yes", "source": "naptan_import", "tactile_paving": "no", "wheelchair": "yes"}}, {"type": "node", "id": 533791000, "lat": 52.2053674, "lon": 0.1239927, "tags": {"bench": "yes", "bin": "yes", "bus": "yes", "highway": "bus_stop", "lit": "yes", "local_ref": "7", "name": "Drummer St Bus Station", "naptan:AtcoCode": "0500CCITY123", "naptan:CommonName": "Drummer St Bus Station", "naptan:Indicator": "Bay 7", "naptan:Landmark": "Bus Station", "naptan:NaptanCode": "cmbdajmd", "naptan:PlusbusZoneRef": "CAMBDGE", "naptan:ShortCommonName": "Drummer St Bay 7", "naptan:Street": "Drummer Street", "naptan:verified": "no", "public_transport": "platform", "shelter": "yes", "source": "naptan_import", "tactile_paving": "no"}}, {"type": "node", "id": 533791001, "lat": 52.2053394, "lon": 0.1240499, "tags": {"bench": "yes", "bin": "yes", "bus": "yes", "highway": "bus_stop", "lit": "yes", "local_ref": "8", "name": "Drummer St Bus Station", "naptan:AtcoCode": "0500CCITY124", "naptan:CommonName": "Drummer St Bus Station", "naptan:Indicator": "Bay 8", "naptan:Landmark": "Bus Station", "naptan:NaptanCode": "cmbdajmg", "naptan:PlusbusZoneRef": "CAMBDGE", "naptan:ShortCommonName": "Drummer St Bay 8", "naptan:Street": "Drummer Street", "naptan:verified": "no", "public_transport": "platform", "shelter": "yes", "source": "naptan_import", "tactile_paving": "no"}}, {"type": "node", "id": 533791006, "lat": 52.2054425, "lon": 0.1238207, "tags": {"bench": "yes", "bin": "yes", "bus": "yes", "highway": "bus_stop", "lit": "yes", "local_ref": "4", "name": "Drummer St Bus Station", "naptan:AtcoCode": "0500CCITY129", "naptan:CommonName": "Drummer St Bus Station", "naptan:Indicator": "Bay 4", "naptan:Landmark": "Bus Station", "naptan:NaptanCode": "cmbdajpa", "naptan:PlusbusZoneRef": "CAMBDGE", "naptan:ShortCommonName": "Drummer St Bay 4", "naptan:Street": "Drummer Street", "naptan:verified": "no", "public_transport": "platform", "shelter": "yes", "source": "naptan_import", "tactile_paving": "no"}}, {"type": "node", "id": 533791065, "lat": 52.2085707, "lon": 0.1184213, "tags": {"bench": "no", "bin": "yes", "bus": "yes", "fixme": "This is a simply hideous collection of bus stop nodes; combine and spit out.", "highway": "bus_stop", "lit": "yes", "name": "Bridge Street", "naptan:AtcoCode": "0500CCITY167", "naptan:Bearing": "SE", "naptan:CommonName": "Bridge Street", "naptan:Crossing": "Round Church Street", "naptan:Indicator": "o/s Round Church", "naptan:Landmark": "Round Church", "naptan:NaptanCode": "cmbdamgj", "naptan:PlusbusZoneRef": "CAMBDGE", "naptan:ShortCommonName": "Round Church", "naptan:Street": "Bridge Street", "naptan:verified": "no", "public_transport": "platform", "shelter": "no", "source": "naptan_import", "tactile_paving": "no"}}, {"type": "node", "id": 533791168, "lat": 52.2052921, "lon": 0.1241794, "tags": {"bench": "yes", "bin": "yes", "bus": "yes", "highway": "bus_stop", "lit": "yes", "local_ref": "10", "name": "Drummer St Bus Station", "naptan:AtcoCode": "0500CCITY227", "naptan:CommonName": "Drummer St Bus Station", "naptan:Indicator": "Bay 10", "naptan:Landmark": "Bus Station Bay 10", "naptan:NaptanCode": "cmbdapjw", "naptan:PlusbusZoneRef": "CAMBDGE", "naptan:ShortCommonName": "Drummer St Bay 10", "naptan:Street": "Drummer Street", "naptan:verified": "no", "public_transport": "platform", "shelter": "yes", "source": "naptan_import", "tactile_paving": "no"}}, {"type": "node", "id": 533791169, "lat": 52.2052641, "lon": 0.1242366, "tags": {"bench": "yes", "bin": "yes", "bus": "yes", "highway": "bus_stop", "lit": "yes", "local_ref": "11", "name": "Drummer St Bus Station", "naptan:AtcoCode": "0500CCITY228", "naptan:CommonName": "Drummer St Bus Station", "naptan:Indicator": "Bay 11", "naptan:Landmark": "Bus Station Bay 11", "naptan:NaptanCode": "cmbdapma", "naptan:PlusbusZoneRef": "CAMBDGE", "naptan:ShortCommonName": "Drummer St  Bay 11", "naptan:Street": "Drummer Street", "naptan:verified": "no", "public_transport": "platform", "shelter": "yes", "source": "naptan_import", "tactile_paving": "no"}}, {"type": "node", "id": 533791170, "lat": 52.2031007, "lon": 0.1300168, "tags": {"bench": "no", "bin": "yes", "bus": "yes", "highway": "bus_stop", "lit": "no", "name": "Parkside", "naptan:AtcoCode": "0500CCITY230", "naptan:Bearing": "SE", "naptan:CommonName": "Parkside", "naptan:Indicator": "SE-bound", "naptan:Landmark": "Fire Station", "naptan:NaptanCode": "cmbdapmg", "naptan:PlusbusZoneRef": "CAMBDGE", "naptan:ShortCommonName": "Parkside", "naptan:Street": "Parkside", "naptan:verified": "no", "note": "Parkside stop.", "operator": "City Sightseeing", "public_transport": "platform", "ref": "11", "shelter": "no", "source": "naptan_import", "tactile_paving": "no"}}, {"type": "node", "id": 533791183, "lat": 52.2123055, "lon": 0.1181485, "tags": {"bench": "no", "bin": "no", "bus": "yes", "check_date:shelter": "2023-12-25", "highway": "bus_stop", "lit": "no", "name": "Hertford Street", "naptan:AtcoCode": "0500CCITY240", "naptan:Bearing": "NE", "naptan:CommonName": "Hertford Street", "naptan:Indicator": "near", "naptan:Landmark": "Hertford Street", "naptan:NaptanCode": "cmbdaptm", "naptan:PlusbusZoneRef": "CAMBDGE", "naptan:ShortCommonName": "Hertford Street", "naptan:Street": "Chesterton Road", "naptan:verified": "no", "note": "Stop for Citi 1 and Citi 2 and 15 and 15A.  Label \"Cambridge  Chesterton Road  Hertford Street\".  Txt msg ref CMBDAPTM", "public_transport": "platform", "shelter": "no", "source": "naptan_import", "tactile_paving": "no"}}, {"type": "node", "id": 533791274, "lat": 52.2053201, "lon": 0.1241222, "tags": {"bench": "yes", "bin": "yes", "bus": "yes", "highway": "bus_stop", "lit": "yes", "local_ref": "9", "name": "Drummer St Bus Station", "naptan:AtcoCode": "0500CCITY274", "naptan:CommonName": "Drummer St Bus Station", "naptan:Indicator": "Bay 9", "naptan:Landmark": "Bus Station Bay 9", "naptan:NaptanCode": "cmbdatjm", "naptan:PlusbusZoneRef": "CAMBDGE", "naptan:ShortCommonName": "Drummer St Bay 9", "naptan:Street": "Drummer Street", "naptan:verified": "no", "public_transport": "platform", "shelter": "yes", "source": "naptan_import", "tactile_paving": "no"}}, {"type": "node", "id": 533791299, "lat": 52.2011957, "lon": 0.1344186, "tags": {"bench": "no", "bin": "no", "bus": "yes", "highway": "bus_stop", "lit": "yes", "name": "Covent Garden", "naptan:AtcoCode": "0500CCITY289", "naptan:Bearing": "SE", "naptan:CommonName": "Covent Garden", "naptan:Indicator": "opp", "naptan:Landmark": "Covent Garden", "naptan:NaptanCode": "cmbdatpm", "naptan:PlusbusZoneRef": "CAMBDGE", "naptan:ShortCommonName": "Covent Garden", "naptan:Street": "Mill Road", "naptan:verified": "no", "public_transport": "platform", "shelter": "yes", "source": "naptan_import", "tactile_paving": "no"}}, {"type": "node", "id": 533791331, "lat": 52.2030803, "lon": 0.1316076, "tags": {"bench": "yes", "bin": "no", "bus": "yes", "highway": "bus_stop", "lit": "yes", "name": "Parkside", "naptan:AtcoCode": "0500CCITY308", "naptan:Bearing": "NE", "naptan:CommonName": "Parkside", "naptan:Indicator": "near", "naptan:Landmark": "Parkside", "naptan:NaptanCode": "cmbdawdj", "naptan:PlusbusZoneRef": "CAMBDGE", "naptan:ShortCommonName": "Parkside", "naptan:Street": "East Road", "naptan:verified": "no", "passenger_information_display": "yes", "public_transport": "platform", "shelter": "yes", "source": "naptan_import", "tactile_paving": "no"}}, {"type": "node", "id": 533791341, "lat": 52.2008624, "lon": 0.1259877, "tags": {"bench": "no", "bin": "no", "bus": "yes", "highway": "bus_stop", "lit": "yes", "name": "Downing College", "naptan:AtcoCode": "0500CCITY320", "naptan:Bearing": "SE", "naptan:CommonName": "Downing College", "naptan:Indicator": "opp", "naptan:Landmark": "Downing College", "naptan:NaptanCode": "cmbdawja", "naptan:PlusbusZoneRef": "CAMBDGE", "naptan:ShortCommonName": "Downing College", "naptan:Street": "Regent Street", "naptan:verified": "no", "public_transport": "platform", "shelter": "no", "source": "naptan_import", "tactile_paving": "no"}}, {"type": "node", "id": 533791342, "lat": 52.2011368, "lon": 0.1256334, "tags": {"bench": "no", "bin": "no", "bus": "yes", "highway": "bus_stop", "lit": "yes", "name": "Downing College", "naptan:AtcoCode": "0500CCITY321", "naptan:Bearing": "NW", "naptan:CommonName": "Downing College", "naptan:Indicator": "o/s", "naptan:Landmark": "Downing College", "naptan:NaptanCode": "cmbdawjd", "naptan:PlusbusZoneRef": "CAMBDGE", "naptan:ShortCommonName": "Downing College", "naptan:Street": "Regent Street", "naptan:verified": "no", "public_transport": "platform", "shelter": "no", "source": "naptan_import", "tactile_paving": "no"}}, {"type": "node", "id": 533791373, "lat": 52.2011521, "lon": 0.1343433, "tags": {"bench": "yes", "bin": "yes", "bus": "yes", "highway": "bus_stop", "lit": "yes", "name": "Covent Garden", "naptan:AtcoCode": "0500CCITY343", "naptan:Bearing": "NW", "naptan:CommonName": "Covent Garden", "naptan:Indicator": "near", "naptan:Landmark": "Covent Garden", "naptan:NaptanCode": "cmbdawtg", "naptan:PlusbusZoneRef": "CAMBDGE", "naptan:ShortCommonName": "Covent Garden", "naptan:Street": "Mill Road", "naptan:verified": "no", "public_transport": "platform", "shelter": "yes", "source": "naptan_import", "tactile_paving": "no"}}, {"type": "node", "id": 533791406, "lat": 52.2021618, "lon": 0.1322111, "tags": {"bench": "no", "bin": "yes", "bus": "yes", "highway": "bus_stop", "lit": "no", "name": "Mortimer Road", "naptan:AtcoCode": "0500CCITY370", "naptan:Bearing": "SE", "naptan:CommonName": "Mortimer Road", "naptan:Indicator": "opp", "naptan:Landmark": "Mortimer Road", "naptan:NaptanCode": "cmbdgamd", "naptan:PlusbusZoneRef": "CAMBDGE", "naptan:ShortCommonName": "Mortimer Road", "naptan:Street": "Mill Road", "naptan:verified": "no", "public_transport": "platform", "shelter": "no", "source": "naptan_import", "tactile_paving": "no"}}, {"type": "node", "id": 533791407, "lat": 52.2015662, "lon": 0.1303386, "tags": {"bench": "yes", "bin": "no", "bus": "yes", "highway": "bus_stop", "lit": "yes", "name": "Gonville Place", "naptan:AtcoCode": "0500CCITY371", "naptan:Bearing": "SW", "naptan:CommonName": "Gonville Place", "naptan:Crossing": "Mill Road", "naptan:Indicator": "SW-bound", "naptan:Landmark": "Parker's Piece", "naptan:NaptanCode": "cmbdgamg", "naptan:PlusbusZoneRef": "CAMBDGE", "naptan:ShortCommonName": "Gonville Place", "naptan:Street": "Gonville Place", "naptan:verified": "no", "public_transport": "platform", "shelter": "yes", "source": "naptan_import", "tactile_paving": "no"}}, {"type": "node", "id": 533791471, "lat": 52.2012495, "lon": 0.1187961, "tags": {"bench": "no", "bin": "no", "bus": "yes", "highway": "bus_stop", "lit": "yes", "name": "Pembroke Street", "naptan:AtcoCode": "0500CCITY419", "naptan:Bearing": "SE", "naptan:CommonName": "Pembroke Street", "naptan:Indicator": "near", "naptan:Landmark": "Pembroke Street", "naptan:NaptanCode": "cmbdgdma", "naptan:PlusbusZoneRef": "CAMBDGE", "naptan:ShortCommonName": "Pembroke Street", "naptan:Street": "Trumpington Street", "naptan:verified": "no", "public_transport": "platform", "shelter": "no", "source": "naptan_import", "tactile_paving": "no"}}, {"type": "node", "id": 533791475, "lat": 52.2015495, "lon": 0.1183562, "tags": {"bench": "no", "bin": "no", "bus": "yes", "check_date:shelter": "2023-09-14", "highway": "bus_stop", "lit": "yes", "name": "Pembroke Street", "naptan:AtcoCode": "0500CCITY420", "naptan:Bearing": "NW", "naptan:CommonName": "Pembroke Street", "naptan:Indicator": "opp", "naptan:Landmark": "Pembroke Street", "naptan:NaptanCode": "cmbdgdmd", "naptan:PlusbusZoneRef": "CAMBDGE", "naptan:ShortCommonName": "Pembroke Street", "naptan:Street": "Trumpington Street", "naptan:verified": "no", "public_transport": "platform", "shelter": "no", "source": "naptan_import", "tactile_paving": "no"}}, {"type": "node", "id": 533791515, "lat": 52.2079787, "lon": 0.1257457, "tags": {"bench": "yes", "bin": "no", "bus": "yes", "departures_board": "timetable", "highway": "bus_stop", "lit": "yes", "name": "Belmont Place", "naptan:AtcoCode": "0500CCITY433", "naptan:Bearing": "E", "naptan:CommonName": "Belmont Place", "naptan:Indicator": "opp", "naptan:Landmark": "Belmont Place", "naptan:NaptanCode": "cmbdgdpt", "naptan:PlusbusZoneRef": "CAMBDGE", "naptan:ShortCommonName": "Belmont Place", "naptan:Street": "Jesus Lane", "naptan:verified": "no", "note": "Also stop 7 (\"Jesus Lane - Towards Rail Station and American Cemetery\") on the Stagecoach City Sightseeing route.", "pole": "yes", "public_transport": "platform", "shelter": "no", "tactile_paving": "no"}}, {"type": "node", "id": 533791617, "lat": 52.2001286, "lon": 0.1282795, "tags": {"bench": "no", "bin": "yes", "bus": "yes", "highway": "bus_stop", "lit": "yes", "name": "Gonville Place", "naptan:AtcoCode": "0500CCITY463", "naptan:Bearing": "NE", "naptan:CommonName": "Gonville Place", "naptan:Indicator": "NE-bound", "naptan:Landmark": "Parker's Piece", "naptan:NaptanCode": "cmbgjaja", "naptan:PlusbusZoneRef": "CAMBDGE", "naptan:ShortCommonName": "Gonville Place", "naptan:Street": "Gonville Place", "naptan:verified": "no", "public_transport": "platform", "shelter": "no", "source": "naptan_import", "tactile_paving": "no"}}, {"type": "node", "id": 533791622, "lat": 52.2034808, "lon": 0.1231119, "tags": {"bench": "no", "bin": "no", "bus": "yes", "highway": "bus_stop", "lit": "yes", "name": "St Andrew's Street", "naptan:AtcoCode": "0500CCITY464", "naptan:Bearing": "NE", "naptan:CommonName": "St Andrew's Street", "naptan:Crossing": "St Andrew's Street", "naptan:Indicator": "near", "naptan:Landmark": "St Andrew's Street", "naptan:NaptanCode": "cmbgjajg", "naptan:PlusbusZoneRef": "CAMBDGE", "naptan:ShortCommonName": "Downing Street DS", "naptan:Street": "Downing Street", "naptan:verified": "no", "public_transport": "platform", "shelter": "no", "source": "naptan_import", "tactile_paving": "no"}}, {"type": "node", "id": 533791664, "lat": 52.203439, "lon": 0.1289164, "tags": {"bench": "yes", "bin": "yes", "bus": "yes", "highway": "bus_stop", "lit": "no", "local_ref": "16", "mapillary": "1108821886253618", "name": "Parkside, 16", "naptan:AtcoCode": "0500CCITY476", "naptan:Bearing": "NW", "naptan:CommonName": "Parkside", "naptan:Crossing": "Warkworth Terrace", "naptan:Indicator": "Bay 16", "naptan:Landmark": "Parker's Piece", "naptan:NaptanCode": "cmbgjmtp", "naptan:PlusbusZoneRef": "CAMBDGE", "naptan:ShortCommonName": "Parkside Bay 16", "naptan:Street": "Parkside", "naptan:verified": "no", "public_transport": "platform", "shelter": "yes", "source": "naptan_import", "survey:date": "2019-02-15", "tactile_paving": "no"}}, {"type": "node", "id": 533791669, "lat": 52.2033378, "lon": 0.1291391, "tags": {"bench": "yes", "bin": "yes", "bus": "yes", "highway": "bus_stop", "lit": "yes", "local_ref": "17", "name": "Parkside, 17", "naptan:AtcoCode": "0500CCITY477", "naptan:Bearing": "NW", "naptan:CommonName": "Parkside", "naptan:Crossing": "Warkworth Terrace", "naptan:Indicator": "Bay 17", "naptan:Landmark": "Parker's Piece", "naptan:NaptanCode": "cmbgjmtw", "naptan:PlusbusZoneRef": "CAMBDGE", "naptan:ShortCommonName": "Parkside Bay 17", "naptan:Street": "Parkside", "naptan:verified": "no", "public_transport": "platform", "ref": "17", "shelter": "yes", "source": "naptan_import", "survey:date": "2019-02-15", "tactile_paving": "no"}}, {"type": "node", "id": 533791674, "lat": 52.2032283, "lon": 0.1294079, "tags": {"bench": "yes", "bin": "yes", "bus": "yes", "highway": "bus_stop", "lit": "no", "local_ref": "18", "name": "Parkside, 18", "naptan:AtcoCode": "0500CCITY478", "naptan:Bearing": "NW", "naptan:CommonName": "Parkside", "naptan:Crossing": "Warkworth Terrace", "naptan:Indicator": "Bay 18", "naptan:Landmark": "Parker's Piece", "naptan:NaptanCode": "cmbgjmwa", "naptan:PlusbusZoneRef": "CAMBDGE", "naptan:ShortCommonName": "Parkside Bay 18", "naptan:Street": "Parkside", "naptan:verified": "no", "public_transport": "platform", "shelter": "yes", "source": "naptan_import", "tactile_paving": "no"}}, {"type": "node", "id": 533791699, "lat": 52.2048443, "lon": 0.1250801, "tags": {"bench": "yes", "bin": "yes", "bus": "yes", "highway": "bus_stop", "lit": "yes", "local_ref": "D3", "name": "Drummer Street", "naptan:AtcoCode": "0500CCITY484", "naptan:Bearing": "W", "naptan:CommonName": "Drummer Street", "naptan:Crossing": "Emmanuel Street", "naptan:Indicator": "Stop D3", "naptan:Landmark": "Emmanuel Street", "naptan:NaptanCode": "cmbgjpwd", "naptan:ShortCommonName": "Drummer St Stop D3", "naptan:Street": "Drummer Street", "naptan:verified": "no", "public_transport": "platform", "shelter": "yes", "source": "naptan_import", "tactile_paving": "no"}}, {"type": "node", "id": 533791702, "lat": 52.2049029, "lon": 0.1248195, "tags": {"bench": "yes", "bin": "no", "bus": "yes", "highway": "bus_stop", "lit": "yes", "local_ref": "D2", "name": "Drummer Street", "naptan:AtcoCode": "0500CCITY485", "naptan:Bearing": "W", "naptan:CommonName": "Drummer Street", "naptan:Crossing": "Emmanuel Street", "naptan:Indicator": "Stop D2", "naptan:Landmark": "Emmanuel Street", "naptan:NaptanCode": "cmbgjpwg", "naptan:PlusbusZoneRef": "CAMBDGE", "naptan:ShortCommonName": "Drummer St Stop D2", "naptan:Street": "Drummer Street", "naptan:verified": "no", "public_transport": "platform", "shelter": "yes", "source": "naptan_import", "tactile_paving": "no"}}, {"type": "node", "id": 533791708, "lat": 52.2049423, "lon": 0.1246311, "tags": {"bench": "yes", "bin": "no", "bus": "yes", "highway": "bus_stop", "lit": "yes", "local_ref": "D1", "name": "Drummer Street", "naptan:AtcoCode": "0500CCITY486", "naptan:Bearing": "W", "naptan:CommonName": "Drummer Street", "naptan:Crossing": "Emmanuel Street", "naptan:Indicator": "Stop D1", "naptan:Landmark": "Emmanuel Street", "naptan:NaptanCode": "cmbgjpwj", "naptan:PlusbusZoneRef": "CAMBDGE", "naptan:ShortCommonName": "Drummer St Stop D1", "naptan:Street": "Drummer Street", "naptan:verified": "no", "public_transport": "platform", "shelter": "yes", "source": "naptan_import", "tactile_paving": "no"}}, {"type": "node", "id": 533791712, "lat": 52.2042836, "lon": 0.1235606, "tags": {"bench": "yes", "bin": "yes", "bus": "yes", "highway": "bus_stop", "lit": "yes", "local_ref": "E1", "name": "Emmanuel Street", "naptan:AtcoCode": "0500CCITY487", "naptan:Bearing": "SW", "naptan:CommonName": "Emmanuel Street", "naptan:Crossing": "St Andrew's Street", "naptan:Indicator": "Stop E1", "naptan:Landmark": "St Andrew's Street", "naptan:NaptanCode": "cmbgjpwm", "naptan:PlusbusZoneRef": "CAMBDGE", "naptan:ShortCommonName": "Emmanuel St Stop E1", "naptan:Street": "Emmanuel Street", "naptan:verified": "no", "public_transport": "platform", "shelter": "yes", "source": "naptan_import", "tactile_paving": "no"}}, {"type": "node", "id": 533791717, "lat": 52.2043572, "lon": 0.1236665, "tags": {"bench": "yes", "bin": "yes", "bus": "yes", "highway": "bus_stop", "lit": "yes", "local_ref": "E2", "name": "Emmanuel Street", "naptan:AtcoCode": "0500CCITY488", "naptan:Bearing": "SW", "naptan:CommonName": "Emmanuel Street", "naptan:Crossing": "St Andrew's Street", "naptan:Indicator": "Stop E2", "naptan:Landmark": "St Andrew's Street", "naptan:NaptanCode": "cmbgjpwp", "naptan:PlusbusZoneRef": "CAMBDGE", "naptan:ShortCommonName": "Emmanuel St Stop E2", "naptan:Street": "Emmanuel Street", "naptan:verified": "no", "public_transport": "platform", "shelter": "yes", "source": "naptan_import", "tactile_paving": "yes"}}, {"type": "node", "id": 533791721, "lat": 52.2046299, "lon": 0.1240015, "tags": {"bench": "yes", "bin": "yes", "bus": "yes", "check_date:shelter": "2025-11-27", "highway": "bus_stop", "lit": "yes", "local_ref": "E3", "name": "Emmanuel Street", "naptan:AtcoCode": "0500CCITY489", "naptan:Bearing": "SW", "naptan:CommonName": "Emmanuel Street", "naptan:Crossing": "St Andrew's Street", "naptan:Indicator": "Stop E3", "naptan:Landmark": "St Andrew's Street", "naptan:NaptanCode": "cmbgjpwt", "naptan:PlusbusZoneRef": "CAMBDGE", "naptan:ShortCommonName": "Emmanuel St Stop E3", "naptan:Street": "Emmanuel Street", "naptan:verified": "no", "public_transport": "platform", "shelter": "yes", "source": "naptan_import", "tactile_paving": "no"}}, {"type": "node", "id": 533791727, "lat": 52.2047442, "lon": 0.1241532, "tags": {"bench": "yes", "bin": "yes", "bus": "yes", "highway": "bus_stop", "lit": "yes", "local_ref": "E4", "name": "Emmanuel Street", "naptan:AtcoCode": "0500CCITY490", "naptan:Bearing": "SW", "naptan:CommonName": "Emmanuel Street", "naptan:Crossing": "St Andrew's Street", "naptan:Indicator": "Stop E4", "naptan:Landmark": "St Andrew's Street", "naptan:NaptanCode": "cmbgjtad", "naptan:PlusbusZoneRef": "CAMBDGE", "naptan:ShortCommonName": "Emmanuel St Stop E4", "naptan:Street": "Emmanuel Street", "naptan:verified": "no", "note": "Citi 5 and Citi 6 buses (which run a circular service) begin/terminate here.", "public_transport": "platform", "shelter": "yes", "source": "naptan_import", "tactile_paving": "no"}}, {"type": "node", "id": 533791733, "lat": 52.2048408, "lon": 0.124275, "tags": {"bench": "yes", "bin": "yes", "bus": "yes", "highway": "bus_stop", "lit": "yes", "local_ref": "E5", "name": "Emmanuel Street", "naptan:AtcoCode": "0500CCITY491", "naptan:Bearing": "SW", "naptan:CommonName": "Emmanuel Street", "naptan:Crossing": "St Andrew's Street", "naptan:Indicator": "Stop E5", "naptan:Landmark": "St Andrew's Street", "naptan:NaptanCode": "cmbgjtag", "naptan:PlusbusZoneRef": "CAMBDGE", "naptan:ShortCommonName": "Emmanuel St Stop E5", "naptan:Street": "Emmanuel Street", "naptan:verified": "no", "public_transport": "platform", "shelter": "yes", "source": "naptan_import", "tactile_paving": "no"}}, {"type": "node", "id": 533791736, "lat": 52.2046863, "lon": 0.1223649, "tags": {"bench": "yes", "bin": "yes", "bus": "yes", "highway": "bus_stop", "lit": "yes", "local_ref": "S1", "name": "St Andrew's Street", "naptan:AtcoCode": "0500CCITY492", "naptan:Bearing": "NW", "naptan:CommonName": "St Andrew's Street", "naptan:Crossing": "Emmanuel Street", "naptan:Indicator": "Stop S1", "naptan:Landmark": "Emmanuel Street", "naptan:NaptanCode": "cmbgjtaj", "naptan:PlusbusZoneRef": "CAMBDGE", "naptan:ShortCommonName": "St Andrew's Stop S1", "naptan:Street": "St Andrew's Street", "naptan:verified": "no", "public_transport": "platform", "shelter": "yes", "source": "naptan_import", "tactile_paving": "no"}}, {"type": "node", "id": 533791739, "lat": 52.2045237, "lon": 0.1225566, "tags": {"bench": "yes", "bin": "yes", "bus": "yes", "highway": "bus_stop", "lit": "yes", "local_ref": "S2", "name": "St Andrew's Street S1", "naptan:AtcoCode": "0500CCITY493", "naptan:Bearing": "NW", "naptan:CommonName": "St Andrew's Street", "naptan:Crossing": "Emmanuel Street", "naptan:Indicator": "Stop S2", "naptan:Landmark": "Emmanuel Street", "naptan:NaptanCode": "cmbgjtam", "naptan:PlusbusZoneRef": "CAMBDGE", "naptan:ShortCommonName": "St Andrew's Stop S2", "naptan:Street": "St Andrew's Street", "naptan:verified": "no", "operator": "C1; C3 (Stagecoach)", "public_transport": "platform", "shelter": "yes", "source": "naptan_import", "tactile_paving": "no"}}, {"type": "node", "id": 533791743, "lat": 52.2044553, "lon": 0.1226952, "tags": {"bench": "yes", "bin": "yes", "bus": "yes", "highway": "bus_stop", "lit": "yes", "local_ref": "S3", "name": "St Andrew's Street S2", "naptan:AtcoCode": "0500CCITY494", "naptan:Bearing": "NW", "naptan:CommonName": "St Andrew's Street", "naptan:Crossing": "Emmanuel Street", "naptan:Indicator": "Stop S3", "naptan:Landmark": "Emmanuel Street", "naptan:NaptanCode": "cmbgjtap", "naptan:PlusbusZoneRef": "CAMBDGE", "naptan:ShortCommonName": "St Andrew's Stop S3", "naptan:Street": "St Andrew's Street", "naptan:verified": "no", "operator": "C2; 17 (Stagecoach)", "public_transport": "platform", "shelter": "yes", "source": "naptan_import", "tactile_paving": "no"}}, {"type": "node", "id": 533791747, "lat": 52.2038661, "lon": 0.1231001, "tags": {"bench": "no", "bin": "yes", "bus": "yes", "check_date": "2025-01-10", "check_date:lit": "2025-01-10", "highway": "bus_stop", "lit": "yes", "local_ref": "4", "mapillary": "182567997047900", "name": "St Andrew's Street", "naptan:AtcoCode": "0500CCITY495", "naptan:Bearing": "NW", "naptan:CommonName": "St Andrew's Street", "naptan:Crossing": "Emmanuel Street", "naptan:Indicator": "Stop 4", "naptan:Landmark": "Emmanuel Street", "naptan:NaptanCode": "cmbgjtat", "naptan:PlusbusZoneRef": "CAMBDGE", "naptan:ShortCommonName": "St Andrew's Stop S4", "naptan:Street": "St Andrew's Street", "naptan:verified": "no", "pole": "yes", "public_transport": "platform", "shelter": "no", "source": "naptan_import", "tactile_paving": "no"}}, {"type": "node", "id": 533791757, "lat": 52.2089786, "lon": 0.1193576, "tags": {"bench": "no", "bin": "no", "bus": "yes", "fixme": "Inaccessible as of 2022-01-09 due to Park St car park works. Where's the replacement?", "highway": "bus_stop", "lit": "yes", "name": "The Busway Park Street", "naptan:AtcoCode": "0500CCITY498", "naptan:Bearing": "NE", "naptan:CommonName": "The Busway Park Street", "naptan:Crossing": "Park Street", "naptan:Indicator": "near", "naptan:Landmark": "Round Church", "naptan:NaptanCode": "cmbgjtmj", "naptan:ShortCommonName": "Busway Park Street", "naptan:Street": "Round Church Street", "naptan:verified": "no", "public_transport": "platform", "shelter": "no", "source": "naptan_import", "tactile_paving": "yes"}}, {"type": "node", "id": 533791758, "lat": 52.2079266, "lon": 0.1196945, "tags": {"bench": "yes", "bin": "yes", "bus": "yes", "highway": "bus_stop", "lit": "yes", "name": "The Busway Cloister Court", "naptan:AtcoCode": "0500CCITY499", "naptan:Bearing": "SW", "naptan:CommonName": "The Busway Cloister Court", "naptan:Crossing": "Sindey Street", "naptan:Indicator": "o/s", "naptan:Landmark": "Sindey Street", "naptan:NaptanCode": "cmbgjtmp", "naptan:ShortCommonName": "Busway Cloister Court", "naptan:Street": "Jesus Lane", "naptan:verified": "no", "public_transport": "platform", "shelter": "yes", "source": "naptan_import", "tactile_paving": "yes"}}, {"type": "node", "id": 533791764, "lat": 52.2068179, "lon": 0.1270831, "tags": {"bench": "yes", "bin": "yes", "bus": "yes", "description": "Bus stop not in use; will become operational when guided busway opens", "highway": "bus_stop", "lit": "yes", "name": "The Busway New Square(opposite)", "naptan:AtcoCode": "0500CCITY500", "naptan:Bearing": "N", "naptan:CommonName": "The Busway New Square", "naptan:Crossing": "New Square", "naptan:Indicator": "opp", "naptan:Landmark": "New Square", "naptan:NaptanCode": "cmbgjtmt", "naptan:ShortCommonName": "Busway New Square", "naptan:Street": "Emmanuel Road", "naptan:verified": "no", "public_transport": "platform", "shelter": "yes", "source": "naptan_import", "tactile_paving": "no"}}, {"type": "node", "id": 533791767, "lat": 52.2067059, "lon": 0.1271813, "tags": {"bench": "yes", "bin": "yes", "bus": "yes", "description": "This bus stop is not in use, c. March 2010.", "highway": "bus_stop", "lit": "yes", "name": "The Busway New Square", "naptan:AtcoCode": "0500CCITY501", "naptan:Bearing": "S", "naptan:CommonName": "The Busway New Square", "naptan:Crossing": "New Square", "naptan:Indicator": "adj", "naptan:Landmark": "New Square", "naptan:NaptanCode": "cmbgjtmw", "naptan:ShortCommonName": "Busway New Square", "naptan:Street": "Emmanuel Road", "naptan:verified": "no", "operator": "stagecoach", "public_transport": "platform", "shelter": "yes", "source": "naptan_import", "tactile_paving": "no"}}, {"type": "node", "id": 533791770, "lat": 52.2027263, "lon": 0.1243905, "tags": {"bench": "no", "bin": "no", "bus": "yes", "highway": "bus_stop", "lit": "yes", "name": "The Busway Church", "naptan:AtcoCode": "0500CCITY502", "naptan:Bearing": "SE", "naptan:CommonName": "The Busway Church", "naptan:Crossing": "Park Terrace", "naptan:Indicator": "opp", "naptan:Landmark": "Baptist Church", "naptan:NaptanCode": "cmbgjtpa", "naptan:ShortCommonName": "Busway Church", "naptan:Street": "St Andrew's Street", "naptan:verified": "no", "public_transport": "platform", "shelter": "no", "source": "naptan_import", "tactile_paving": "no"}}, {"type": "node", "id": 533791823, "lat": 52.2077635, "lon": 0.1282493, "tags": {"bench": "no", "bin": "no", "bus": "yes", "highway": "bus_stop", "lit": "yes", "name": "Fair Street", "naptan:AtcoCode": "0500CCITY515", "naptan:Bearing": "W", "naptan:CommonName": "Fair Street", "naptan:Indicator": "near", "naptan:Landmark": "Victoria Avenue", "naptan:NaptanCode": "cmbgjwmd", "naptan:ShortCommonName": "Fair Street", "naptan:Street": "Maids Causeway", "naptan:verified": "no", "public_transport": "platform", "shelter": "no", "source": "naptan_import", "tactile_paving": "no"}}, {"type": "node", "id": 533791826, "lat": 52.2079975, "lon": 0.125336, "tags": {"bench": "no", "bin": "no", "bus": "yes", "check_date": "2025-05-29", "check_date:bench": "2025-05-29", "check_date:bin": "2025-05-29", "check_date:lit": "2025-05-29", "check_date:tactile_paving": "2025-05-29", "departures_board": "timetable", "highway": "bus_stop", "lit": "yes", "mapillary": "252127873331784", "name": "Belmont Place", "naptan:AtcoCode": "0500CCITY516", "naptan:Bearing": "W", "naptan:CommonName": "Belmont Place", "naptan:Indicator": "near", "naptan:Landmark": "Belmont Place", "naptan:NaptanCode": "cmbgjtpj", "naptan:ShortCommonName": "Belmont Place", "naptan:Street": "Jesus Lane", "naptan:verified": "no", "pole": "yes", "public_transport": "platform", "shelter": "no", "tactile_paving": "no"}}]}